recursivenamespace/__init__.py
recursivenamespace/_version.py
recursivenamespace/_version_pdm.py
recursivenamespace/main.py
recursivenamespace/utils.py
recursivenamespacev2-0.0.2.dist-info/METADATA
recursivenamespacev2-0.0.2.dist-info/WHEEL
recursivenamespacev2-0.0.2.dist-info/entry_points.txt
recursivenamespacev2-0.0.2.dist-info/licenses/LICENSE
recursivenamespacev2-0.0.2.dist-info/RECORD
