Metadata-Version: 2.1
Name: RecursiveNamespaceV2
Version: 0.0.2
Summary: Recursive Namespace. An extension of SimpleNamespace. Enhance get/set and parse from JSON
Author-Email: VienPQ <pasxd245@gmail.com>
License: MIT License
Classifier: Programming Language :: Python :: 3
Classifier: License :: OSI Approved :: MIT License
Classifier: Operating System :: OS Independent
Project-URL: homepage, https://github.com/pasxd245/RecursiveNamespaceV2
Project-URL: repository, https://github.com/pasxd245/RecursiveNamespaceV2
Requires-Python: >=3.8
Provides-Extra: test
Requires-Dist: pytest>=6.0; extra == "test"
Requires-Dist: coverage>=7.0; extra == "test"
